{
  "products": [
    {
      "id": 1,
      "name": "بلاستيك شفاف PVC",
      "price": 96,
      "unit": "جنيه / كيلو",
      "tag": "متوفر بجميع التخانات",
      "old_price": null,
      "details": [
        "خامة P.V.C شفافة مبدره",
        "سوبر كلير عالي الجودة",
        "عرض 150 سم",
        "متوفر جميع التخانات",
        "مقاوم للماء والرطوبة"
      ]
    },
    {
      "id": 2,
      "name": "سوست ألوان 5 م",
      "price": 210,
      "unit": "جنيه / الرول",
      "tag": "جميع الألوان",
      "old_price": 230,
      "details": [
        "سوست جميع الألوان",
        "طول 100 ياردة للرول",
        "مقاس 5 متر",
        "جودة عالية وممتازة",
        "مناسب لجميع الاستخدامات"
      ]
    },
    {
      "id": 3,
      "name": "سوست 5 م أسود",
      "price": 185,
      "unit": "جنيه / الرول",
      "tag": "كلاسيكي",
      "old_price": null,
      "details": [
        "سوست أسود كلاسيكي",
        "طول 100 ياردة للرول",
        "مقاس 5 متر",
        "جودة ممتازة ومتانة عالية",
        "مناسب للملابس والحقائب"
      ]
    },
    {
      "id": 4,
      "name": "سوست روز 5 ملي",
      "price": 200,
      "unit": "جنيه / الرول",
      "tag": "عرض خاص 🔥",
      "old_price": 250,
      "details": [
        "سوست روز مميز",
        "طول 100 ياردة للرول",
        "مقاس 5 ملي",
        "جودة عالية",
        "عرض لفترة محدودة"
      ]
    }
  ],
  "promo": {
    "active": true,
    "text": "عرض خاص لفترة محدودة! سوست روز 5 ملي - 100 ياردة بـ",
    "price": 200,
    "old_price": 250,
    "unit": "جنيه فقط"
  },
  "exportDate": "2026-06-02T13:14:15.692Z"
}